kanban/__init__.py
kanban/__main__.py
kanban/config.ini
kanban/config.py
kanban/version.py
kanban/app/__init__.py
kanban/app/app_facade.py
kanban/app/command/__init__.py
kanban/app/command/board_commands.py
kanban/app/command/column_commands.py
kanban/app/command/command.py
kanban/app/command/dispatcher.py
kanban/app/command/task_commands.py
kanban/app/controller/__init__.py
kanban/app/controller/cli_controller.py
kanban/app/controller/module.py
kanban/app/service/__init__.py
kanban/app/service/board_service.py
kanban/app/service/column_service.py
kanban/app/service/module.py
kanban/app/service/service.py
kanban/app/service/task_service.py
kanban/domain/__init__.py
kanban/domain/error.py
kanban/domain/model/__init__.py
kanban/domain/model/board.py
kanban/domain/model/column.py
kanban/domain/model/entity.py
kanban/domain/model/task.py
kanban/domain/model/state/__init__.py
kanban/domain/model/state/board_state.py
kanban/domain/model/state/column_state.py
kanban/domain/model/state/task_state.py
kanban/domain/service/__init__.py
kanban/domain/service/model_composition.py
kanban/domain/service/model_identity.py
kanban/domain/service/model_index.py
kanban/infra/__init__.py
kanban/infra/cmdline/__init__.py
kanban/infra/cmdline/cli_parser.py
kanban/infra/data/__init__.py
kanban/infra/data/data_facade.py
kanban/infra/data/data_manager.py
kanban/infra/data/mapper/__init__.py
kanban/infra/data/mapper/placeholder.py
kanban/infra/data/mapper/type_adapter.py
kanban/infra/data/repo/__init__.py
kanban/infra/data/repo/board_repo.py
kanban/infra/data/repo/column_repo.py
kanban/infra/data/repo/factory.py
kanban/infra/data/repo/repository.py
kanban/infra/data/repo/table.py
kanban/infra/data/repo/task_repo.py
kanban/interface/__init__.py
kanban/interface/cmdline/__init__.py
kanban/interface/cmdline/view.py
kanban-0.1.0.dist-info/LICENSE
kanban-0.1.0.dist-info/METADATA
kanban-0.1.0.dist-info/WHEEL
kanban-0.1.0.dist-info/entry_points.txt
kanban-0.1.0.dist-info/top_level.txt
kanban-0.1.0.dist-info/RECORD
