Metadata-Version: 2.1
Name: kanban
Version: 0.1.0
Summary: Kanban application
Home-page: https://github.com/Tastyep/Kanban
Author: Luc Sinet
Author-email: luc.sinet@gmail.com
License: MIT
Platform: UNKNOWN
Classifier: Programming Language :: Python :: 3
Classifier: Programming Language :: Python :: 3.7
Classifier: License :: OSI Approved :: MIT License
Classifier: Operating System :: OS Independent
